cortic/__init__.py
cortic/cli.py
cortic-0.1.0.dist-info/entry_points.txt
cortic-0.1.0.dist-info/WHEEL
cortic-0.1.0.dist-info/METADATA
cortic-0.1.0.dist-info/RECORD
