Metadata-Version: 2.1
Name: cortic
Version: 0.1.0
Summary: 
Author: Seth Juarez
Requires-Python: >=3.9,<4.0
Classifier: Programming Language :: Python :: 3
Classifier: Programming Language :: Python :: 3.10
Classifier: Programming Language :: Python :: 3.9
Requires-Dist: click (>=8.0.3,<9.0.0)
Requires-Dist: mlflow (>=1.23.1,<2.0.0)
